{"pageProps":{"ciudad":{"acf":{"horario_especial":false,"ciudad_oro":"benidorm","direccion":"Calle Valencia 4, local 3B","como_llegar":"","email_tienda":"benidorm@quickgold.es","telefono":"966 391 392","enlace_facebook":"https://www.facebook.com/quickgold.benidorm","maseg":"0.5","solo_imagen":false,"imagen_banner_desktop":"https://quickgold.es/wp-content/uploads/2021/11/banner-web-black-friday21-escritorio.jpg","imagen_banner_mobile":"https://quickgold.es/wp-content/uploads/2021/11/banner-web-black-friday21-movil.jpg","tienda":"benidorm","nombre_tienda":"Quickgold Benidorm","mobile":"613 48 44 98","place_id":"ChIJqQ93O_kFYg0RtRpYKUTWR_0","website":"/benidorm","yelp":"","foursquare":"","bing":"","paginas_amarillas":"","interes_standard":"5","tasacion":"100","promo_empeno":false,"promo_activa":false,"coste_de_tasacion":"3","id":"224342","vende_divisa":false,"id_programa":"79","ciudad_landing":"Benidorm","mapa_landing":"https://www.google.com/maps/embed?pb=!1m18!1m12!1m3!1d3120.875001501314!2d-0.12870258439146828!3d38.53664947573176!2m3!1f0!2f0!3f0!3m2!1i1gold%20Ben024!2i768!4f13.1!3m3!1m2!1s0xd6205f93b770fa9%3A0xfd47d64429581ab5!2sQuickidorm%20-%20Compro%20Oro%20%7C%20Casa%20de%20Cambio!5e0!3m2!1ses!2ses!4v1680512530459!5m2!1ses!2ses","enlace_resenas":"https://www.google.com/search?q=quickgold%20benidorm&oq=quickgold+brnidorm&aqs=chrome..69i57j0i13i512.5032j0j4&sourceid=chrome&ie=UTF-8&tbs=lf:1,lf_ui:10&tbm=lcl&sxsrf=ALiCzsZChkd8fV3zg37vBC-u2MGwPaNbzw:1672387360327&rflfq=1&num=10&rldimm=18250791603181984437&lqi=ChJxdWlja2dvbGQgYmVuaWRvcm1I-NK7o5GxgIAIWhoQABgAGAEiEnF1aWNrZ29sZCBiZW5pZG9ybZIBC2dvbGRfZGVhbGVyqgEREAEqDSIJcXVpY2tnb2xkKA4&phdesc=qMSLVw6d77M&ved=2ahUKEwi02ae08KD8AhUaVKQEHaYsASIQvS56BAgLEAE&sa=X&rlst=f#rlfi=hd:;si:18250791603181984437,l,ChJxdWlja2dvbGQgYmVuaWRvcm1I-NK7o5GxgIAIWhoQABgAGAEiEnF1aWNrZ29sZCBiZW5pZG9ybZIBC2dvbGRfZGVhbGVyqgEREAEqDSIJcXVpY2tnb2xkKA4,y,qMSLVw6d77M;mv:[[41.3207229,1.3892247],[38.1753163,-3.9513967]];tbs:lrf:!1m4!1u3!2m2!3m1!1e1!1m4!1u2!2m2!2m1!1e1!2m1!1e2!2m1!1e3!3sIAE,lf:1,lf_ui:10","foto_1":"https://quickgold.es/wp-content/uploads/2023/02/3-min.jpg","foto_2":"https://quickgold.es/wp-content/uploads/2023/02/6-min.jpg","foto_3":"https://quickgold.es/wp-content/uploads/2023/02/4-min.jpg","escribir_resenas_landings":"http://bit.ly/3jxGuNY","url_resenas":"3jxGuNY","para_mas_de_plata":"10","para_mas_de_oro":"100","precio_mas_de_plata":"20","precio_mas_de_oro":"0.35","promo_activa_cambiardivisa":false,"promo_activa_empenarjoyas":false,"promo_activa_preciodeloro":false,"promo_general_activa":false,"imagen_cambiardivisa_desktop":"","imagen_cambiardivisa_mobil":"","imagen_preciodeloro_desktop":"","imagen_preciodeloro_mobil":"","imagen_empenarjoyas_desktop":"","imagen_empenarjoyas_mobil":"","imagen_general_desktop":"","imagen_general_mobil":"","script_chat":"","nonscript_chat":"","primer_mes":"0","promo_activa_invertirenoro":false,"imagen_invertirenoro_desktop":"","imagen_invertirenoro_mobil":"","titulo_del_meta":"","descripcion_del_meta":"","titulo_del_h1":"","canonical":"","texto_boton_llamar":""}},"tiendaGoogle":{"html_attributions":[],"result":{"address_components":[{"long_name":"local 3B","short_name":"local 3B","types":["subpremise"]},{"long_name":"4","short_name":"4","types":["street_number"]},{"long_name":"Calle de Valencia","short_name":"C. de Valencia","types":["route"]},{"long_name":"Benidorm","short_name":"Benidorm","types":["locality","political"]},{"long_name":"Alicante","short_name":"A","types":["administrative_area_level_2","political"]},{"long_name":"Comunidad Valenciana","short_name":"VC","types":["administrative_area_level_1","political"]},{"long_name":"España","short_name":"ES","types":["country","political"]},{"long_name":"03503","short_name":"03503","types":["postal_code"]}],"adr_address":"<span class=\"street-address\">C. de Valencia, 4</span>, local 3B, <span class=\"postal-code\">03503</span> <span class=\"locality\">Benidorm</span>, <span class=\"region\">Alicante</span>, <span class=\"country-name\">España</span>","business_status":"OPERATIONAL","current_opening_hours":{"open_now":true,"periods":[{"close":{"date":"2023-07-10","day":1,"time":"2100"},"open":{"date":"2023-07-10","day":1,"time":"0900"}},{"close":{"date":"2023-07-11","day":2,"time":"2100"},"open":{"date":"2023-07-11","day":2,"time":"0900"}},{"close":{"date":"2023-07-12","day":3,"time":"2100"},"open":{"date":"2023-07-12","day":3,"time":"0900"}},{"close":{"date":"2023-07-13","day":4,"time":"2100"},"open":{"date":"2023-07-13","day":4,"time":"0900"}},{"close":{"date":"2023-07-14","day":5,"time":"2100"},"open":{"date":"2023-07-14","day":5,"time":"0900"}},{"close":{"date":"2023-07-15","day":6,"time":"1500"},"open":{"date":"2023-07-15","day":6,"time":"0900"}}],"weekday_text":["lunes: 9:00–21:00","martes: 9:00–21:00","miércoles: 9:00–21:00","jueves: 9:00–21:00","viernes: 9:00–21:00","sábado: 9:00–15:00","domingo: Cerrado"]},"formatted_address":"C. de Valencia, 4, local 3B, 03503 Benidorm, Alicante, España","formatted_phone_number":"966 39 13 92","geometry":{"location":{"lat":38.5366453,"lng":-0.1265139},"viewport":{"northeast":{"lat":38.53797033029149,"lng":-0.125270269708498},"southwest":{"lat":38.5352723697085,"lng":-0.127968230291502}}},"icon":"https://maps.gstatic.com/mapfiles/place_api/icons/v1/png_71/shopping-71.png","icon_background_color":"#4B96F3","icon_mask_base_uri":"https://maps.gstatic.com/mapfiles/place_api/icons/v2/shopping_pinlet","international_phone_number":"+34 966 39 13 92","name":"Quickgold Benidorm - Compro Oro | Money Exchange","opening_hours":{"open_now":true,"periods":[{"close":{"day":1,"time":"2100"},"open":{"day":1,"time":"0900"}},{"close":{"day":2,"time":"2100"},"open":{"day":2,"time":"0900"}},{"close":{"day":3,"time":"2100"},"open":{"day":3,"time":"0900"}},{"close":{"day":4,"time":"2100"},"open":{"day":4,"time":"0900"}},{"close":{"day":5,"time":"2100"},"open":{"day":5,"time":"0900"}},{"close":{"day":6,"time":"1500"},"open":{"day":6,"time":"0900"}}],"weekday_text":["lunes: 9:00–21:00","martes: 9:00–21:00","miércoles: 9:00–21:00","jueves: 9:00–21:00","viernes: 9:00–21:00","sábado: 9:00–15:00","domingo: Cerrado"]},"photos":[{"height":3000,"html_attributions":["<a href=\"https://maps.google.com/maps/contrib/106985791763660003964\">Quickgold Benidorm - Compro Oro | Money Exchange</a>"],"photo_reference":"Aaw_FcJEjAHXcePgbleRgXyfKpqP41whML4z3s7QMFoKXOgMpgSGJOPoZ5ixdGGPnRkLkW_8tDs4EZIxRwS-lDXGGiRsA2V0s2c7cJ1n0hu8mzVImByQzAAmoxdWqKPIB204HIFzBf-phez6lOaNny2wfmS1tdgsVB5OLzgddAlXkQu_xomy","width":4000},{"height":3000,"html_attributions":["<a href=\"https://maps.google.com/maps/contrib/106985791763660003964\">Quickgold Benidorm - Compro Oro | Money Exchange</a>"],"photo_reference":"Aaw_FcIj9H1H5kw5-nPjnfY3ExE12GhpFQOwrJvmJZYIo1ZAgym9Fs4xvPYRlNdHDnQWolf7Y2kG5vuJvHF-2-LWI6mxjWFqTX9D6iFO0MepiPaxC-SWIyMw7_MMteoaOr-qzLaI_gM0AQxOQvR4bHt9Nh4NolXJGAir6xRPy60VDQmOnmsS","width":4000},{"height":3648,"html_attributions":["<a href=\"https://maps.google.com/maps/contrib/103767884857385033941\">Isa Cuadros</a>"],"photo_reference":"Aaw_FcLIAwT4vDf8ZZJ-9HWpDRcy8xNyYMjbwYLHNONZdcgu53fr8kMCAK6-LV3K4QVeMRAa03PxkOSfEBw2J-s8bDHHS5cq5gESx1KX5Jv1thVTEBEB3yeS0Wax0cBFywI5F_DYjcRH7RYuPLunb9XjlEI4pi4fKBE9jdxjgdT-AvgFBubM","width":2736},{"height":608,"html_attributions":["<a href=\"https://maps.google.com/maps/contrib/106985791763660003964\">Quickgold Benidorm - Compro Oro | Money Exchange</a>"],"photo_reference":"Aaw_FcLe4b8FxpHIKZnD0B1Wd0v3L6gr1zQktqOXpXHXLtfmaRKCir-ooAC9-oEgQwfVAiRhZYOp3SPOrQ7H5Dwl0B7IoDOEm_alJi-SNMRBe6BMFyEMkHKHmMhoOyE54VH_7-oXfWccafroiyNCcq6EscOfl7ccoBmweJGXMfMpZcPebClg","width":1080},{"height":4032,"html_attributions":["<a href=\"https://maps.google.com/maps/contrib/111596260138736261539\">Maryandrea Rodriguez Malpica</a>"],"photo_reference":"Aaw_FcLTGiJlyURMeQ7_Fqy6n-InR8gwWYJDQkNJXljzKZE1TCg8VXqh1c3kwKquc7iPntnHels2ZOH7r2c-uNslGqlWfCv2RS64HNU-rmfp5I2ciUfL9RCI_qfAfXC-4oTGPkprCHS5dmujSqFTFsHbS3vNwYkNnig9lCKKR311v_LApUpE","width":3024},{"height":3000,"html_attributions":["<a href=\"https://maps.google.com/maps/contrib/106985791763660003964\">Quickgold Benidorm - Compro Oro | Money Exchange</a>"],"photo_reference":"Aaw_FcJW9zT9IBFCPVHXvxPbpSAY2opveiiH4NT_OaQcMeDtqIgD9NayNezAL8MXd2VG34-14W77Px8-wnZBmExVe7s_joQSieKDJq8ivc_mOXQgiyY8iVOLM91ipJtn9riAa6qrXVBZ0O6ZEIG5CMzv0Lvjyddj6uhsuLmYTmHkVU__yw0f","width":4000},{"height":4000,"html_attributions":["<a href=\"https://maps.google.com/maps/contrib/106985791763660003964\">Quickgold Benidorm - Compro Oro | Money Exchange</a>"],"photo_reference":"Aaw_FcLvx5RsNHJjYJMc1Jo9TMQnGCwzeLg-_75YoXIpc01A2WfjiQwvqEhV4GK1nAq9eWPGOp3HpWJVlxP9T_tvl-vI6DK7eFjndhbRNp2ucoeTZy281C2cxoMN2LeK-6oXnJ9yLjqSJ7KFEmjjxQFMZGTSNTFnyR4bt8t-pz9Wc7Xw7co2","width":3000},{"height":2874,"html_attributions":["<a href=\"https://maps.google.com/maps/contrib/106985791763660003964\">Quickgold Benidorm - Compro Oro | Money Exchange</a>"],"photo_reference":"Aaw_FcIOvjG00EdXVDQgYVxCoKkpHh5wtz-5KUnfXv9zmROAY6nvnppCKoCnjsNrXJb-ZN0uwzQ_v4_r2C8hYgSGTLO_dF2P3G4spIEZh35C3eF1JEBce_jfLFrIy2NDfWy1zAuGkB6F-GC1HBBl2mi2IamgEqj3y-Eyxtcvo7M3FyWZX2Kc","width":2990}],"place_id":"ChIJqQ93O_kFYg0RtRpYKUTWR_0","plus_code":{"compound_code":"GVPF+M9 Benidorm, España","global_code":"8CCXGVPF+M9"},"rating":5,"reference":"ChIJqQ93O_kFYg0RtRpYKUTWR_0","reviews":[{"author_name":"Lorenzo martin molina","author_url":"https://www.google.com/maps/contrib/109050682633663200612/reviews","language":"es","original_language":"es","profile_photo_url":"https://lh3.googleusercontent.com/a-/AD_cMMTvPJ4hvmuZIH4mSo-EY4KQs6M9ZIBhDznnVoecs8nL_j7S=s128-c0x00000000-cc-rp-mo","rating":5,"relative_time_description":"Hace 1 mes","text":"Fue el pasado sábado, 27, a vender una cantidad de oro, que tenía guardada de la herencia de mi padre. Y tengo que decir que el sitio está muy limpio, muy bien ubicado y en todo momento fueron muy profesionales conmigo. Tengo que estar muy agradecido que me atendió un chico que se llama DANIEL, que en todo momento, fue muy selectivo con las piezas, para darme el mejor precio por su distinto tipo de kilates. MUY RECOMENDABLE. Sin duda, si tengo que volver a vender oro,volveré otra vez!!","time":1685427215,"translated":false},{"author_name":"Sara Sherine","author_url":"https://www.google.com/maps/contrib/116025179651812955883/reviews","language":"es","original_language":"es","profile_photo_url":"https://lh3.googleusercontent.com/a/AAcHTteLXHpK9AwYQlGt2CsVsxo2oc2eq2Pfn3gRLANzbxke=s128-c0x00000000-cc-rp-mo","rating":5,"relative_time_description":"Hace una semana","text":"Tengo que dar las gracias a CAROLINA, que en todo momento era muy profesional, muy paciente y me explico todo en detalle sobre las piezas de oro que lleve. Si tenéis que vender oro o simplemente queréis saber el valor que tiene, no lo dudéis...Si queréis el mejor precio por quilate y muy buena atención al cliente hay que ir a Quickgold Benidorm. Muchas gracias CAROLINA...","time":1687893263,"translated":false},{"author_name":"Krislaine Orellana","author_url":"https://www.google.com/maps/contrib/103916528127112302779/reviews","language":"es","original_language":"es","profile_photo_url":"https://lh3.googleusercontent.com/a/AAcHTted0YeKFQH0p0_NkLUrGQ0tiBNyt8H7H0eXLp3tMOwL=s128-c0x00000000-cc-rp-mo","rating":5,"relative_time_description":"en la última semana","text":"Excelente atención de Karolina atenta a resolver todas mis\ndudas, gracias por el servicio! Altamente recomendable.","time":1688513215,"translated":false},{"author_name":"Isa Cuadros","author_url":"https://www.google.com/maps/contrib/103767884857385033941/reviews","language":"es","original_language":"es","profile_photo_url":"https://lh3.googleusercontent.com/a-/AD_cMMR4hSF5tigYBBqVatImt5U5IiAp2KvvGtBAxNWROTOvFhrT=s128-c0x00000000-cc-rp-mo-ba5","rating":5,"relative_time_description":"Hace 1 mes","text":"Muy amable y muy buen servicio de compra venta de oro. Recomiendo 100%","time":1683914560,"translated":false},{"author_name":"Jota P","author_url":"https://www.google.com/maps/contrib/106848124464796226855/reviews","language":"es","original_language":"es","profile_photo_url":"https://lh3.googleusercontent.com/a/AAcHTtc2RgWEtCIBZJyQpZeEKHnq3H5iWNKkYBuFDjUyQPgO=s128-c0x00000000-cc-rp-mo","rating":5,"relative_time_description":"Hace 1 mes","text":"Hola, soy cliente habitual y en todas las ocasiones que realice operaciones fui excelentemente atendido por Karolina, siempre amable y atenta a las mejoras de tipos de cambio para la divisa. Recomiendo la oficina. Muchas gracias","time":1684428471,"translated":false}],"types":["jewelry_store","finance","point_of_interest","store","establishment"],"url":"https://maps.google.com/?cid=18250791603181984437","user_ratings_total":107,"utc_offset":120,"vicinity":"Calle de Valencia, 4, local 3B, Benidorm","website":"https://quickgold.es/tiendas/compro-oro-benidorm/calle-valencia-4-local-3b/?utm_source=gmb&utm_medium=boton&utm_content&utm_campaign=sitio-web-gmb"},"status":"OK"},"general":{"acf":{"telefono":"912 29 68 55","meta_titulo":"Quickgold Alcobendas | Compro oro, empeños y cambio de divisa","meta_descripcion":"Tienda Quickgold en C/ De Manuel Serrano Frutos 2, Alcobendas. La franquicia mejor valorada de España para vender oro, empeñar joyas y cambiar divisa.","telefono_mobil":"601218789","url_mapa_popup":"https://www.google.com/maps/embed?pb=!1m14!1m8!1m3!1d12127.384084245063!2d-3.6421282!3d40.5449909!3m2!1i1024!2i768!4f13.1!3m3!1m2!1s0x0%3A0xb6a21d506fd75755!2sQuickgold%20Alcobendas%20-%20Compro%20Oro%20%26%20Money%20Exchange!5e0!3m2!1ses!2ses!4v1653387579763!5m2!1ses!2ses","ciudad":"Alcobendas","url_dejanos_opinion":"https://www.google.com/maps/place/Quickgold+Alcobendas+-+Compro+Oro+%26+Money+Exchange/@40.5449909,-3.6421282,17z/data=!3m1!4b1!4m5!3m4!1s0xd422cf2ccc34fc1:0xb6a21d506fd75755!8m2!3d40.5449888!4d-3.6421238","url_resenas":"https://www.google.com/maps/place/Quickgold+Alcal%C3%A1+de+Henares+-+Compro+Oro+%26+Money+Exchange/@40.4862186,-3.3611423,17z/data=!4m7!3m6!1s0xd424949fa5a52b5:0x12f73ce8892ee23d!8m2!3d40.4862186!4d-3.3589536!9m1!1b1","tienda":"","ciudad_oro":"","place_id":"","website":"","nombre_tienda":"","direccion":"","como_llegar":"","email_tienda":"","mobile":"","enlace_facebook":"","yelp":"","foursquare":"","bing":"","paginas_amarillas":"","id_programa":"","ciudad_landing":"","mapa_landing":"","enlace_resenas":"","foto_1":"","foto_2":"","foto_3":"","escribir_resenas_landings":"","script_chat":"","nonscript_chat":"","para_mas_de_plata":"","para_mas_de_oro":"","precio_mas_de_plata":"","precio_mas_de_oro":"","promo_activa_cambiardivisa":false,"promo_activa_empenarjoyas":false,"promo_activa_preciodeloro":false,"promo_general_activa":false,"imagen_cambiardivisa_desktop":"https://quickgold.es/wp-content/uploads/2022/11/banner_web_desktop.jpg","imagen_cambiardivisa_mobil":"","imagen_preciodeloro_desktop":"","imagen_preciodeloro_mobil":"","imagen_empenarjoyas_desktop":"https://quickgold.es/wp-content/uploads/2022/11/banner_web_desktop.jpg","imagen_empenarjoyas_mobil":"","imagen_general_desktop":"https://quickgold.es/wp-content/uploads/2023/01/Alcobendas-web.png","imagen_general_mobil":"","promo_activa_invertirenoro":false,"imagen_invertirenoro_desktop":"","imagen_invertirenoro_mobil":""}}},"__N_SSG":true}